dp_redo/__init__.py
dp_redo/logging.py
dp_redo/redo.py
dp_redo/version.py
dp_redo-3.0.2.dist-info/LICENSE
dp_redo-3.0.2.dist-info/METADATA
dp_redo-3.0.2.dist-info/WHEEL
dp_redo-3.0.2.dist-info/top_level.txt
dp_redo-3.0.2.dist-info/RECORD
