Metadata-Version: 2.1
Name: dp-redo
Version: 3.0.2
Summary: A python variant of the redo build system, with which You Can (Not) Redo.
Home-page: https://github.com/dontpanic92/dp-redo
Author: Shengqiu Li
Author-email: lishengqiu.hit@gmail.com
License: UNKNOWN
Platform: UNKNOWN
Classifier: Programming Language :: Python :: 3
Classifier: License :: OSI Approved :: MIT License
Classifier: Operating System :: OS Independent
Requires-Python: >=3.6
